competitions_cup-0.5.1-py2.7-nspkg.pth
competitions/cup/__init__.py
competitions/cup/default/poweroftwo_double.py
competitions/cup/default/StandardSingleEliminationCup.py
competitions/cup/default/single_elimination.py
competitions/cup/default/PowerOfTwoLosersBracket.py
competitions/cup/default/PowerOfTwoDoubleEliminationCup.py
competitions/cup/default/stepladder.py
competitions/cup/default/PowerOfTwoSingleEliminationCup.py
competitions/cup/default/StepladderCup.py
competitions/cup/default/__init__.py
competitions_cup-0.5.1.dist-info/METADATA
competitions_cup-0.5.1.dist-info/DESCRIPTION.rst
competitions_cup-0.5.1.dist-info/RECORD
competitions_cup-0.5.1.dist-info/WHEEL
competitions_cup-0.5.1.dist-info/top_level.txt
competitions_cup-0.5.1.dist-info/namespace_packages.txt
competitions_cup-0.5.1.dist-info/metadata.json
