Metadata-Version: 2.0
Name: competitions-cup
Version: 0.5.1
Summary: Generic cup competitions
Home-page: https://github.com/happy5214/competitions-cup
Author: Alexander Jones
Author-email: happy5214@gmail.com
License: LGPLv3+
Keywords: competitions cups knockout elimination
Platform: UNKNOWN
Classifier: Development Status :: 3 - Alpha
Classifier: License :: OSI Approved :: GNU Lesser General Public License v3 or later (LGPLv3+)
Classifier: Programming Language :: Python :: 2.7
Classifier: Programming Language :: Python :: 3.2
Classifier: Programming Language :: Python :: 3.3
Classifier: Programming Language :: Python :: 3.4
Requires-Dist: competitions-match (>=0.3)
